image_processing/__init__.py
image_processing/processing/__init__.py
image_processing/processing/combination.py
image_processing/processing/transformation.py
image_processing/utils/__init__.py
image_processing/utils/io.py
image_processing/utils/plot.py
pacote_processamento_de_imagens-0.0.1.dist-info/METADATA
pacote_processamento_de_imagens-0.0.1.dist-info/WHEEL
pacote_processamento_de_imagens-0.0.1.dist-info/top_level.txt
pacote_processamento_de_imagens-0.0.1.dist-info/RECORD
