Metadata-Version: 2.1
Name: pacote-processamento-de-imagens
Version: 0.0.1
Summary: Pacote de processamento de imagens
Home-page: https://github.com/SEPalmiere/DIO_Unimed_Ciencia_Dados
Author: Sergio Eduardo Palmiere
Author-email: palmiere@hotmail.com
License: UNKNOWN
Platform: UNKNOWN
Requires-Python: >=3.8
Requires-Dist: matplotlib
Requires-Dist: numpy
Requires-Dist: scikit-image (>=0.16.1)
